TerraformLibrary/__init__.py
TerraformLibrary/terraformlibrary.py
robotframework_terraformlibrary-0.2.0.dist-info/LICENSE
robotframework_terraformlibrary-0.2.0.dist-info/METADATA
robotframework_terraformlibrary-0.2.0.dist-info/WHEEL
robotframework_terraformlibrary-0.2.0.dist-info/RECORD
