Metadata-Version: 2.3
Name: robotframework-terraformlibrary
Version: 0.2.0
Summary: A Robotframework Library wrapping the Terraform CLI
License: Apache-2.0
Author: Nils Balkow-Tychsen
Maintainer: Nils Balkow-Tychsen
Requires-Python: >=3.10,<4.0
Classifier: License :: OSI Approved :: Apache Software License
Classifier: Programming Language :: Python :: 3
Classifier: Programming Language :: Python :: 3.10
Classifier: Programming Language :: Python :: 3.11
Classifier: Programming Language :: Python :: 3.12
Classifier: Programming Language :: Python :: 3.13
Requires-Dist: robotframework (>=7)
Requires-Dist: robotframework-pythonlibcore (>=4)
Project-URL: Homepage, https://github.com/nilsty/robotframework-terraformlibrary
